bbpn/__init__.py
bbpn/bbpn.py
bbpn-1.0.dist-info/LICENSE
bbpn-1.0.dist-info/METADATA
bbpn-1.0.dist-info/WHEEL
bbpn-1.0.dist-info/top_level.txt
bbpn-1.0.dist-info/RECORD
